odoo9_addon_partner_password_reset-9.0.1.0.0-py2.7-nspkg.pth
odoo9_addon_partner_password_reset-9.0.1.0.0.dist-info/DESCRIPTION.rst
odoo9_addon_partner_password_reset-9.0.1.0.0.dist-info/METADATA
odoo9_addon_partner_password_reset-9.0.1.0.0.dist-info/RECORD
odoo9_addon_partner_password_reset-9.0.1.0.0.dist-info/WHEEL
odoo9_addon_partner_password_reset-9.0.1.0.0.dist-info/metadata.json
odoo9_addon_partner_password_reset-9.0.1.0.0.dist-info/namespace_packages.txt
odoo9_addon_partner_password_reset-9.0.1.0.0.dist-info/top_level.txt
odoo_addons/partner_password_reset/README.rst
odoo_addons/partner_password_reset/__init__.py
odoo_addons/partner_password_reset/__openerp__.py
odoo_addons/partner_password_reset/tests/__init__.py
odoo_addons/partner_password_reset/tests/test_res_partner_password_reset_wizard.py
odoo_addons/partner_password_reset/wizard/__init__.py
odoo_addons/partner_password_reset/wizard/res_partner_password_reset_wizard.py
odoo_addons/partner_password_reset/wizard/res_partner_password_reset_wizard_view.xml
